study_pet/__init__.py
study_pet/__main__.py
study_pet/data_manager.py
study_pet/tracker.py
study_pet/pet/__init__.py
study_pet/pet/actions.py
study_pet/pet/core.py
study_pet-0.1.0.dist-info/licenses/LICENSE
study_pet-0.1.0.dist-info/METADATA
study_pet-0.1.0.dist-info/WHEEL
study_pet-0.1.0.dist-info/entry_points.txt
study_pet-0.1.0.dist-info/top_level.txt
study_pet-0.1.0.dist-info/RECORD
