Metadata-Version: 2.4
Name: study-pet
Version: 0.1.0
Summary: A Python package to gamify your study sessions by raising a virtual ball python
Author-email: Catherine Yu <catherine@example.com>, Leo Fu <leo@example.com>, JunHao Chen <junhao@example.com>, Majo Salgado <majo@example.com>, Zeba Shafi <zeba@example.com>
License: MIT
Project-URL: Homepage, https://github.com/swe-students-fall2025/3-python-package-team_cascade
Project-URL: Repository, https://github.com/swe-students-fall2025/3-python-package-team_cascade
Project-URL: Issues, https://github.com/swe-students-fall2025/3-python-package-team_cascade/issues
Keywords: study,productivity,gamification,pet,cli,ball-python
Classifier: Development Status :: 3 - Alpha
Classifier: Intended Audience :: Education
Classifier: License :: OSI Approved :: MIT License
Classifier: Programming Language :: Python :: 3
Classifier: Programming Language :: Python :: 3.10
Classifier: Programming Language :: Python :: 3.11
Classifier: Programming Language :: Python :: 3.12
Classifier: Programming Language :: Python :: 3.13
Classifier: Topic :: Education
Requires-Python: >=3.10
License-File: LICENSE
Dynamic: license-file
